focalnet_tensorflow/__init__.py
focalnet_tensorflow/blocks.py
focalnet_tensorflow/create_focalnet_model.py
focalnet_tensorflow/focalnet.py
focalnet_tensorflow/layers.py
focalnet_tensorflow-0.0.6.dist-info/METADATA
focalnet_tensorflow-0.0.6.dist-info/WHEEL
focalnet_tensorflow-0.0.6.dist-info/top_level.txt
focalnet_tensorflow-0.0.6.dist-info/RECORD
